lvmtipo/__init__.py
lvmtipo/actors.py
lvmtipo/ambient.py
lvmtipo/command.py
lvmtipo/exceptions.py
lvmtipo/fiber.py
lvmtipo/fieldrot/__init__.py
lvmtipo/fieldrot/__main__.py
lvmtipo/focus.py
lvmtipo/homtrans.py
lvmtipo/kmirror.py
lvmtipo/mirror.py
lvmtipo/pwimount.py
lvmtipo/scraper.py
lvmtipo/siderostat.py
lvmtipo/site.py
lvmtipo/target.py
lvmtipo/util/keep_alive.py
lvmtipo/util/keyreader.py
lvmtipo/wcsarith.py
sdss_lvmtipo-0.2.1.dist-info/LICENSE.md
sdss_lvmtipo-0.2.1.dist-info/METADATA
sdss_lvmtipo-0.2.1.dist-info/WHEEL
sdss_lvmtipo-0.2.1.dist-info/entry_points.txt
sdss_lvmtipo-0.2.1.dist-info/RECORD
