Metadata-Version: 2.1
Name: sdss-lvmtipo
Version: 0.2.1
Summary: Additional functionality for sdss-clu
Home-page: https://github.com/sdss/lvmtipo
License: BSD-3-Clause
Keywords: astronomy,software
Author: Florian Briegel
Author-email: briegel@mpia.de
Requires-Python: >=3.8,<4
Classifier: Intended Audience :: Science/Research
Classifier: License :: OSI Approved :: BSD License
Classifier: Natural Language :: English
Classifier: Operating System :: OS Independent
Classifier: Programming Language :: Python :: 3
Classifier: Programming Language :: Python :: 3.8
Classifier: Programming Language :: Python :: 3.9
Classifier: Programming Language :: Python :: 3.10
Classifier: Programming Language :: Python :: 3.11
Classifier: Topic :: Documentation :: Sphinx
Classifier: Topic :: Software Development :: Libraries :: Python Modules
Requires-Dist: astropy (>=5.2)
Requires-Dist: click-default-group (>=1.2.2,<2.0.0)
Requires-Dist: sdss-cluplus (>=0.1.3)
Project-URL: Documentation, https://sdss-lvmtipo.readthedocs.org
Project-URL: Repository, https://github.com/sdss/lvmtipo
